algormeter/__init__.py
algormeter/algormeter.py
algormeter/perfprof.py
algormeter/algorithms/__init__.py
algormeter/algorithms/algorithms.py
algormeter/kernel/__init__.py
algormeter/kernel/kernel.py
algormeter/libs/DCJBKMLib.py
algormeter/libs/__init__.py
algormeter/libs/data.py
algormeter/libs/probLib.py
algormeter/tools/__init__.py
algormeter/tools/counter.py
algormeter/tools/dbx.py
algormeter-1.1.1.dist-info/METADATA
algormeter-1.1.1.dist-info/WHEEL
algormeter-1.1.1.dist-info/RECORD
