Metadata-Version: 2.1
Name: algormeter
Version: 1.1.1
Summary: Tool for developing, testing and measuring optimizers algorithms
Project-URL: Homepage, https://github.com/xedla/algormeter.git
Project-URL: Bug Tracker, https://github.com/xedla/algormeter/issues
Author-email: Pietro d Alessandro <pietrodalessandro@gmail.com>
Keywords: convex-optimization,difference-convex-function,optimization-algorithms
Classifier: License :: OSI Approved :: GNU General Public License v3 or later (GPLv3+)
Classifier: Operating System :: OS Independent
Classifier: Programming Language :: Python :: 3
Classifier: Topic :: Scientific/Engineering :: Mathematics
Requires-Python: >=3.10
Requires-Dist: matplotlib
Requires-Dist: numpy
Requires-Dist: pandas
